lemonai/__init__.py
lemonai/api_wrapper.py
lemonai/execute_workflow.py
lemonai/filter_tools.py
lemonai/get_integrations.py
lemonai/tool.py
lemonai/toolkit.py
lemonai/workflow.py
lemonai-0.1.4.dist-info/METADATA
lemonai-0.1.4.dist-info/WHEEL
lemonai-0.1.4.dist-info/licenses/LICENSE
lemonai-0.1.4.dist-info/RECORD
