Metadata-Version: 2.1
Name: lemonai
Version: 0.1.4
Summary: Lemon AI's A Python client. Grant your LLM agents access to a wide range of APIs for read and write operations, creating copilots in minutes and unlocking the true potential of LLMs.
Project-URL: Homepage, https://github.com/felixbrock/lemonai-py-client
Project-URL: Bug Tracker, https://github.com/felixbrock/lemonai-py-client/issues
Author-email: Felix Brockmeier <fe.brockmeier@gmail.com>
License-File: LICENSE
Classifier: License :: OSI Approved :: Apache Software License
Classifier: Operating System :: OS Independent
Classifier: Programming Language :: Python :: 3
Requires-Python: >=3.8.1
Requires-Dist: langchain
Requires-Dist: loguru
